tests/__init__.py
tests/test_todx.py
todx/__init__.py
todx/fabric.py
todx/filehandler-test.py
todx/filehandler.py
todx/main.py
todx/parse_functions.py
todx/searcher.py
todx/settings.py
todx/yesnoquery.py
todx-0.1.3.dist-info/LICENSE
todx-0.1.3.dist-info/METADATA
todx-0.1.3.dist-info/WHEEL
todx-0.1.3.dist-info/entry_points.txt
todx-0.1.3.dist-info/top_level.txt
todx-0.1.3.dist-info/RECORD
