Metadata-Version: 2.1
Name: todx
Version: 0.1.3
Summary: A simple todo application
Home-page: https://github.com/xypnox/todxpy
Author: xypnox
Author-email: xypnox@gmail.com
License: UNKNOWN
Platform: UNKNOWN
Classifier: Programming Language :: Python :: 3
Classifier: License :: OSI Approved :: GNU General Public License v2 (GPLv2)
Classifier: Operating System :: OS Independent
Requires-Dist: appdirs
Requires-Dist: fuzzywuzzy[speedup]
